BrailleToKorean/BrailleData.py
BrailleToKorean/BrailleToKor.py
BrailleToKorean/KorData.py
BrailleToKorean/NumberFunc.py
BrailleToKorean/PunctuationFunc.py
BrailleToKorean/__init__.py
brailletokorean-1.0.3.dist-info/METADATA
brailletokorean-1.0.3.dist-info/WHEEL
brailletokorean-1.0.3.dist-info/licenses/LICENSE.txt
brailletokorean-1.0.3.dist-info/RECORD
